{
  "version": "5",
  "dialect": "sqlite",
  "id": "f9f1f74d-661a-4675-8fe3-7a928c61c8f6",
  "prevId": "6a3cf2a5-9e4b-4a64-bd72-48ae3a19ad35",
  "tables": {
    "user": {
      "name": "user",
      "columns": {
        "id": {
          "name": "id",
          "type": "text",
          "primaryKey": true,
          "notNull": true,
          "autoincrement": false
        }
      },
      "indexes": {},
      "foreignKeys": {},
      "compositePrimaryKeys": {},
      "uniqueConstraints": {}
    }
  },
  "enums": {},
  "_meta": {
    "schemas": {},
    "tables": {},
    "columns": {}
  }
}